{"cp": 24157, "municipio": "Carmen", "ciudad": "Ciudad del Carmen", "estado": "Campeche", "areas": [{"name": "Buenavista", "type": "Fraccionamiento"}, {"name": "Turquesa", "type": "Fraccionamiento"}, {"name": "Rinconada", "type": "Fraccionamiento"}, {"name": "Residencial Vistancias", "type": "Fraccionamiento"}, {"name": "Club Residencial Azul", "type": "Fraccionamiento"}, {"name": "Mar Azul", "type": "Fraccionamiento"}, {"name": "Bicentenario", "type": "Unidad habitacional"}, {"name": "Paseo de los Bosques", "type": "Fraccionamiento"}, {"name": "Puesta del Sol", "type": "Fraccionamiento"}, {"name": "San Joaqu\u00edn", "type": "Colonia"}, {"name": "Santa Isabel", "type": "Fraccionamiento"}, {"name": "Residencial San Miguel", "type": "Fraccionamiento"}, {"name": "Privada Santa Ana", "type": "Fraccionamiento"}, {"name": "Privada San Joaqu\u00edn", "type": "Fraccionamiento"}, {"name": "Playa Palmas", "type": "Fraccionamiento"}, {"name": "Las Esperanzas", "type": "Fraccionamiento"}, {"name": "Real del Carmen", "type": "Fraccionamiento"}, {"name": "Hacienda Dorada", "type": "Fraccionamiento"}, {"name": "Girasoles", "type": "Fraccionamiento"}, {"name": "Ra\u00edces", "type": "Fraccionamiento"}, {"name": "Villas del Carmen", "type": "Fraccionamiento"}, {"name": "Villa Magna", "type": "Fraccionamiento"}, {"name": "Villa Marina", "type": "Fraccionamiento"}, {"name": "Misi\u00f3n del Carmen", "type": "Fraccionamiento"}, {"name": "Reforma II Secci\u00f3n", "type": "Fraccionamiento"}, {"name": "La Esperanza", "type": "Fraccionamiento"}, {"name": "Evergre\u00e9n", "type": "Fraccionamiento"}, {"name": "Jos\u00e9 Ortiz \u00c1vila", "type": "Colonia"}, {"name": "Hacienda del Mar", "type": "Fraccionamiento"}, {"name": "San Rom\u00e1n", "type": "Fraccionamiento"}, {"name": "Canter\u00edas", "type": "Fraccionamiento"}, {"name": "Villa Palmeras", "type": "Fraccionamiento"}, {"name": "18 de Marzo", "type": "Fraccionamiento"}, {"name": "Privanzas", "type": "Fraccionamiento"}]}