{"cp": 27054, "municipio": "Torre\u00f3n", "ciudad": "Torre\u00f3n", "estado": "Coahuila de Zaragoza", "areas": [{"name": "Privadas de Santa Fe", "type": "Fraccionamiento"}, {"name": "Valle Revoluci\u00f3n", "type": "Colonia"}, {"name": "Valle Verde", "type": "Colonia"}, {"name": "La Cortina", "type": "Colonia"}, {"name": "Ciudad Nazas Pol\u00edgono 24 A", "type": "Colonia"}, {"name": "Pedregal del Valle", "type": "Fraccionamiento"}, {"name": "El Pedregal", "type": "Colonia"}, {"name": "Rinc\u00f3n de los Nogales", "type": "Fraccionamiento"}, {"name": "Rinc\u00f3n del Pedregal", "type": "Fraccionamiento"}, {"name": "La Amistad", "type": "Fraccionamiento"}, {"name": "Hacienda la Noria", "type": "Fraccionamiento"}, {"name": "Chapultepec", "type": "Fraccionamiento"}, {"name": "El Kiosco", "type": "Fraccionamiento"}, {"name": "Parque Industrial la Amistad", "type": "Zona industrial"}, {"name": "Ciudad Nazas Pol\u00edgono 24", "type": "Fraccionamiento"}, {"name": "Quintas del Nazas", "type": "Fraccionamiento"}, {"name": "Residencial Victoria", "type": "Fraccionamiento"}, {"name": "Villas Centenario", "type": "Fraccionamiento"}]}