{"cp": 28983, "municipio": "Villa de \u00c1lvarez", "ciudad": "Ciudad de Villa de \u00c1lvarez", "estado": "Colima", "areas": [{"name": "Valle del Sol", "type": "Fraccionamiento"}, {"name": "Puerta Higueras", "type": "Fraccionamiento"}, {"name": "Jardines del Llano", "type": "Colonia"}, {"name": "Rinconada del Centenario", "type": "Colonia"}, {"name": "Jardines del Centenario", "type": "Colonia"}, {"name": "Alfonso Rol\u00f3n Michel", "type": "Colonia"}, {"name": "Tabachines", "type": "Fraccionamiento"}, {"name": "Senderos de Rancho Blanco", "type": "Colonia"}, {"name": "Villa Flores", "type": "Colonia"}, {"name": "Villas Rancho Blanco", "type": "Colonia"}, {"name": "El Haya", "type": "Fraccionamiento"}, {"name": "Puerta de Rol\u00f3n", "type": "Fraccionamiento"}, {"name": "Residencial Tulipanes", "type": "Fraccionamiento"}, {"name": "Villa Flores II", "type": "Colonia"}]}