{"cp": 29034, "municipio": "Tuxtla Guti\u00e9rrez", "ciudad": "Tuxtla Guti\u00e9rrez", "estado": "Chiapas", "areas": [{"name": "Asturias", "type": "Colonia"}, {"name": "Bosques del Parque", "type": "Colonia"}, {"name": "Brasilia", "type": "Colonia"}, {"name": "La Pimienta", "type": "Colonia"}, {"name": "Rinc\u00f3n de La Florida", "type": "Colonia"}, {"name": "Montebello", "type": "Colonia"}, {"name": "Roc\u00edo", "type": "Fraccionamiento"}, {"name": "Quetzalcoatl", "type": "Conjunto habitacional"}]}