{"cp": 29610, "municipio": "Tecpat\u00e1n", "ciudad": "29611", "estado": "Chiapas", "areas": [{"name": "El Ed\u00e9n", "type": "Barrio"}, {"name": "Tecpatan", "type": "Pueblo"}, {"name": "Jorge Guzm\u00e1n", "type": "Colonia"}, {"name": "Framboy\u00e1n", "type": "Colonia"}, {"name": "Luis Donaldo Colosio", "type": "Colonia"}, {"name": "Costa de Oro", "type": "Colonia"}, {"name": "El Triunfo", "type": "Colonia"}, {"name": "El Ed\u00e9n", "type": "Ejido"}, {"name": "El Pocito", "type": "Barrio"}]}