{"cp": 31106, "municipio": "Chihuahua", "ciudad": "Chihuahua", "estado": "Chihuahua", "areas": [{"name": "Continental", "type": "Colonia"}, {"name": "\u00c1ngeles", "type": "Fraccionamiento"}, {"name": "San Guillermo", "type": "Fraccionamiento"}, {"name": "Reforma", "type": "Fraccionamiento"}, {"name": "San Vicente", "type": "Colonia"}, {"name": "R\u00edo Grande", "type": "Colonia"}, {"name": "Quintas del R\u00edo", "type": "Fraccionamiento"}, {"name": "Rinc\u00f3n Colonial", "type": "Fraccionamiento"}]}