{"cp": 33815, "municipio": "Hidalgo del Parral", "ciudad": "Hidalgo del Parral", "estado": "Chihuahua", "areas": [{"name": "San Uriel INFONAVIT", "type": "Colonia"}, {"name": "H\u00e9roes de la Revoluci\u00f3n", "type": "Colonia"}, {"name": "Monta\u00f1as", "type": "Fraccionamiento"}, {"name": "El Polvor\u00edn", "type": "Colonia"}, {"name": "San Rafael", "type": "Fraccionamiento"}, {"name": "Rinconadas del Sol", "type": "Colonia"}, {"name": "Juan Rangel de Biesca", "type": "Colonia"}, {"name": "Real de Victoria", "type": "Fraccionamiento"}, {"name": "Las Palmas", "type": "Fraccionamiento"}]}