{"cp": 34960, "municipio": "Pueblo Nuevo", "ciudad": "34941", "estado": "Durango", "areas": [{"name": "El Zapote [De Pueblo Nuevo]", "type": "Rancher\u00eda"}, {"name": "Pie de Cuesta", "type": "Rancher\u00eda"}, {"name": "Pueblo Nuevo (Pueblo de Ca\u00f1a)", "type": "Pueblo"}, {"name": "Corralitos [De Pueblo Nuevo]", "type": "Rancher\u00eda"}, {"name": "Jag\u00fceyes", "type": "Rancher\u00eda"}, {"name": "La Escondida [De Corralitos]", "type": "Rancher\u00eda"}, {"name": "La Puerta", "type": "Rancher\u00eda"}, {"name": "El Coscomate [De Pueblo Nuevo]", "type": "Rancher\u00eda"}, {"name": "El Ranchito [De Portales de Milpillas]", "type": "Rancher\u00eda"}, {"name": "El Tri\u00e1ngulo", "type": "Rancher\u00eda"}, {"name": "Palo Gordo", "type": "Rancher\u00eda"}, {"name": "Portales de Milpillas", "type": "Rancher\u00eda"}, {"name": "Carric\u00edllos", "type": "Rancher\u00eda"}, {"name": "Las Flores", "type": "Rancher\u00eda"}, {"name": "Los Barbechos", "type": "Rancher\u00eda"}, {"name": "Piedra Ancha", "type": "Rancher\u00eda"}, {"name": "Vaquer\u00eda Dos", "type": "Rancher\u00eda"}]}