{"cp": 37128, "municipio": "Le\u00f3n", "ciudad": "Le\u00f3n de los Aldama", "estado": "Guanajuato", "areas": [{"name": "Los Alpes Residencial", "type": "Fraccionamiento"}, {"name": "Pirules Residencial", "type": "Fraccionamiento"}, {"name": "Cumbres del Campestre", "type": "Fraccionamiento"}, {"name": "Jardines del Campestre", "type": "Colonia"}, {"name": "Real Campestre", "type": "Fraccionamiento"}, {"name": "Se\u00f1ora Frausto", "type": "Colonia"}, {"name": "Punta Campestre", "type": "Colonia"}, {"name": "Torre Cumbres", "type": "Conjunto habitacional"}, {"name": "Misi\u00f3n La Ca\u00f1ada", "type": "Residencial"}]}