{"cp": 40130, "municipio": "Huitzuco de los Figueroa", "ciudad": "Huitzuco", "estado": "Guerrero", "areas": [{"name": "Los Ojitos", "type": "Colonia"}, {"name": "Sentimientos de la Naci\u00f3n", "type": "Colonia"}, {"name": "El Mirador", "type": "Colonia"}, {"name": "Benito Ju\u00e1rez", "type": "Colonia"}, {"name": "Cantarranas", "type": "Colonia"}, {"name": "Huitzuco Centro", "type": "Colonia"}, {"name": "Cristo Rey", "type": "Colonia"}, {"name": "Chapulixtlal", "type": "Colonia"}, {"name": "Ejidal", "type": "Colonia"}, {"name": "Vicente Guerrero (El Bonete)", "type": "Colonia"}, {"name": "El Lucero", "type": "Colonia"}, {"name": "El Real", "type": "Colonia"}, {"name": "La Lama", "type": "Colonia"}, {"name": "Las Pilitas", "type": "Colonia"}, {"name": "Las Trincheras", "type": "Colonia"}, {"name": "Los Pilares", "type": "Colonia"}, {"name": "La Nopalera", "type": "Colonia"}, {"name": "Salcingo", "type": "Colonia"}, {"name": "El Tanque Rojo", "type": "Colonia"}, {"name": "Tepeyac", "type": "Colonia"}, {"name": "20 de Noviembre", "type": "Colonia"}, {"name": "28 de Febrero", "type": "Colonia"}, {"name": "Los Guajitos", "type": "Colonia"}, {"name": "Emiliano Zapata", "type": "Colonia"}, {"name": "La Cruz", "type": "Colonia"}, {"name": "Brisas del Real", "type": "Colonia"}, {"name": "La Joya", "type": "Colonia"}, {"name": "El Llano", "type": "Colonia"}]}