{"cp": 43422, "municipio": "Huehuetla", "ciudad": "43601", "estado": "Hidalgo", "areas": [{"name": "Chapingo", "type": "Rancher\u00eda"}, {"name": "Santa In\u00e9s", "type": "Pueblo"}, {"name": "Aztl\u00e1n", "type": "Barrio"}, {"name": "Cerro de Chapingo", "type": "Rancher\u00eda"}, {"name": "Cerro del Tomate", "type": "Rancher\u00eda"}, {"name": "Chicontla", "type": "Rancher\u00eda"}, {"name": "El Plan del Recreo", "type": "Colonia"}, {"name": "Hermanos Galeana", "type": "Rancher\u00eda"}, {"name": "Piedras Negras", "type": "Rancher\u00eda"}]}