{"cp": 45380, "municipio": "Amatit\u00e1n", "ciudad": "46401", "estado": "Jalisco", "areas": [{"name": "Las Norias", "type": "Colonia"}, {"name": "El Monte", "type": "Colonia"}, {"name": "Lomas de la Cruz", "type": "Colonia"}, {"name": "Hacienda San Jos\u00e9 del Refugio", "type": "Colonia"}, {"name": "La Orillita", "type": "Colonia"}, {"name": "La Bolsa", "type": "Colonia"}, {"name": "5 de Mayo", "type": "Colonia"}, {"name": "El Cerrito", "type": "Colonia"}, {"name": "La Loma", "type": "Colonia"}, {"name": "Amatitan", "type": "Pueblo"}, {"name": "Santiaguito", "type": "Congregaci\u00f3n"}, {"name": "Don Bosco", "type": "Fraccionamiento"}, {"name": "Vivienda Popular", "type": "Colonia"}, {"name": "Venaderos las Norias", "type": "Fraccionamiento"}, {"name": "Ejidal", "type": "Colonia"}, {"name": "Godoy", "type": "Colonia"}, {"name": "Obrera Heliodoro Hern\u00e1ndez Loza", "type": "Colonia"}, {"name": "Jardines de La Cruz", "type": "Colonia"}, {"name": "Puerta Del Sol", "type": "Colonia"}]}