{"cp": 48902, "municipio": "Autl\u00e1n de Navarro", "ciudad": "Autl\u00e1n de Navarro", "estado": "Jalisco", "areas": [{"name": "Azucarera", "type": "Colonia"}, {"name": "Rodriguez Alcaine", "type": "Colonia"}, {"name": "La Noria Infonavit", "type": "Colonia"}, {"name": "Rinconada El Cangrejo", "type": "Colonia"}, {"name": "Puerta de La Costa", "type": "Colonia"}, {"name": "Jardines Del Sol", "type": "Colonia"}, {"name": "Magisterial", "type": "Fraccionamiento"}, {"name": "Jardines Autl\u00e1n", "type": "Colonia"}, {"name": "Colonos Alameda", "type": "Colonia"}, {"name": "Las Am\u00e9ricas", "type": "Colonia"}, {"name": "Paulino Navarro", "type": "Colonia"}, {"name": "La Herradura", "type": "Colonia"}, {"name": "Las Parotitas", "type": "Colonia"}, {"name": "Bugambilias", "type": "Colonia"}]}