{"cp": 50228, "municipio": "Toluca", "ciudad": "50091", "estado": "M\u00e9xico", "areas": [{"name": "Geo Villas de la Ind", "type": "Unidad habitacional"}, {"name": "La Arboleda IV", "type": "Fraccionamiento"}, {"name": "La Arboleda", "type": "Fraccionamiento"}, {"name": "Geovillas los Cedros", "type": "Unidad habitacional"}, {"name": "Las Fuentes", "type": "Condominio"}, {"name": "Villa de San Andr\u00e9s", "type": "Fraccionamiento"}, {"name": "Los Sabinos", "type": "Fraccionamiento"}, {"name": "Geo Villas de la Ind. II", "type": "Fraccionamiento"}, {"name": "La Crespa", "type": "Barrio"}, {"name": "La Arboleda V", "type": "Fraccionamiento"}, {"name": "Las Fuentes Ind.", "type": "Unidad habitacional"}, {"name": "Las Fuentes del Ordal", "type": "Fraccionamiento"}]}