{"cp": 50674, "municipio": "San Jos\u00e9 del Rinc\u00f3n", "ciudad": "50602", "estado": "M\u00e9xico", "areas": [{"name": "Los Pintados (El Pintado)", "type": "Rancher\u00eda"}, {"name": "San Antonio Pueblo Nuevo", "type": "Pueblo"}, {"name": "Santa Rita Pueblo Nuevo", "type": "Rancher\u00eda"}, {"name": "El Lindero Pueblo Nuevo", "type": "Rancher\u00eda"}, {"name": "El Pintado Pueblo Nuevo", "type": "Barrio"}, {"name": "Santa Ana Pueblo Nuevo", "type": "Barrio"}, {"name": "El Cuarenta y Cuatro Pueblo Nuevo", "type": "Rancher\u00eda"}, {"name": "El Cerrito Pueblo Nuevo", "type": "Rancher\u00eda"}, {"name": "Agua Zarca Pueblo Nuevo", "type": "Pueblo"}, {"name": "Santa Cruz Pueblo Nuevo", "type": "Barrio"}, {"name": "De Dolores", "type": "Rancher\u00eda"}]}