{"cp": 60897, "municipio": "Aquila", "ciudad": "60984", "estado": "Michoac\u00e1n de Ocampo", "areas": [{"name": "Corralitos", "type": "Rancho"}, {"name": "El B\u00e1lsamo", "type": "Rancho"}, {"name": "El Bonete", "type": "Rancho"}, {"name": "El Calabozo", "type": "Rancho"}, {"name": "El Canal Agro", "type": "Rancho"}, {"name": "El Cuirindo", "type": "Rancho"}, {"name": "El Higueral (La Higuerita)", "type": "Rancho"}, {"name": "El Ranchito", "type": "Rancho"}, {"name": "El Socorro", "type": "Rancho"}, {"name": "El Varil", "type": "Rancho"}, {"name": "El V\u00e1stago", "type": "Rancho"}, {"name": "La Ceiba", "type": "Rancho"}, {"name": "La Higuera", "type": "Rancho"}, {"name": "La Higuerita Dos", "type": "Rancho"}, {"name": "La Pe\u00f1a", "type": "Rancho"}, {"name": "La Sierrita", "type": "Rancho"}, {"name": "Las Calandrias", "type": "Rancho"}, {"name": "Las Playas", "type": "Rancho"}, {"name": "Limonera de Basilio", "type": "Rancho"}, {"name": "Los Puertecitos", "type": "Rancho"}, {"name": "Ojos de Agua", "type": "Rancho"}, {"name": "Puerto del Toro", "type": "Rancho"}]}