{"cp": 62553, "municipio": "Jiutepec", "ciudad": "Jiutepec", "estado": "Morelos", "areas": [{"name": "Constituci\u00f3n", "type": "Colonia"}, {"name": "Residencial Campestre", "type": "Unidad habitacional"}, {"name": "Tlahuapan", "type": "Colonia"}, {"name": "Residencial La Palma", "type": "Fraccionamiento"}, {"name": "Moctezuma", "type": "Colonia"}, {"name": "Insurgentes", "type": "Unidad habitacional"}, {"name": "La Rosa", "type": "Unidad habitacional"}, {"name": "L\u00e1zaro C\u00e1rdenas", "type": "Colonia"}, {"name": "Rinconada las Palmas", "type": "Unidad habitacional"}, {"name": "El Arroyo", "type": "Fraccionamiento"}, {"name": "Lirios", "type": "Fraccionamiento"}, {"name": "Bamb\u00fa", "type": "Fraccionamiento"}, {"name": "Residencial Country", "type": "Fraccionamiento"}, {"name": "Tlahua", "type": "Fraccionamiento"}, {"name": "Arcos de Jiutepec", "type": "Unidad habitacional"}, {"name": "Villa Real", "type": "Fraccionamiento"}, {"name": "Campestre", "type": "Fraccionamiento"}]}