{"cp": 66072, "municipio": "General Escobedo", "ciudad": "Ciudad General Escobedo", "estado": "Nuevo Le\u00f3n", "areas": [{"name": "Brianzzas Residencial", "type": "Fraccionamiento"}, {"name": "La Providencia", "type": "Fraccionamiento"}, {"name": "Mirador del Valle", "type": "Fraccionamiento"}, {"name": "Mirasur II", "type": "Fraccionamiento"}, {"name": "Parque Industrial Libramiento", "type": "Zona industrial"}, {"name": "Bosques de Escobedo", "type": "Colonia"}, {"name": "Hacienda del Topo", "type": "Colonia"}, {"name": "Progreso Paso Cucharas", "type": "Colonia"}, {"name": "Quinto Centenario", "type": "Colonia"}, {"name": "Hacienda los Ayala", "type": "Colonia"}, {"name": "Cortijo los Ayala", "type": "Fraccionamiento"}, {"name": "Paseo Real", "type": "Fraccionamiento"}, {"name": "Renacimiento", "type": "Fraccionamiento"}, {"name": "Hacienda los Vergeles", "type": "Fraccionamiento"}]}