{"cp": 73566, "municipio": "Cuetzalan del Progreso", "ciudad": "73561", "estado": "Puebla", "areas": [{"name": "Tzinacapan", "type": "Pueblo"}, {"name": "Xaltipan", "type": "Rancher\u00eda"}, {"name": "Yohualichan", "type": "Pueblo"}, {"name": "Ayotzinapan", "type": "Pueblo"}, {"name": "Cozamalomila", "type": "Rancher\u00eda"}, {"name": "Kapola", "type": "Rancher\u00eda"}, {"name": "Limonco", "type": "Rancher\u00eda"}, {"name": "Pinahuista", "type": "Pueblo"}, {"name": "Reyeshogpan de Hidalgo", "type": "Pueblo"}, {"name": "Santioapan", "type": "Rancher\u00eda"}, {"name": "Tacuapan", "type": "Pueblo"}, {"name": "Tecoltepec", "type": "Pueblo"}, {"name": "Tepetit\u00e1n Reyeshogpan de Hidalgo", "type": "Pueblo"}, {"name": "Tepetzintan", "type": "Pueblo"}, {"name": "Tuzamapan (Xiloxochico)", "type": "Pueblo"}, {"name": "Xalcuahuta", "type": "Pueblo"}]}