{"cp": 78597, "municipio": "Charcas", "ciudad": "Charcas", "estado": "San Luis Potos\u00ed", "areas": [{"name": "Clavellina", "type": "Barrio"}, {"name": "Lomas de Santa Mar\u00eda", "type": "Barrio"}, {"name": "La Luz", "type": "Barrio"}, {"name": "IMMSA", "type": "Colonia"}, {"name": "El Mineral", "type": "Colonia"}, {"name": "INFONAVIT", "type": "Colonia"}, {"name": "La Esperanza", "type": "Fraccionamiento"}, {"name": "El Grasero", "type": "Barrio"}, {"name": "El Minero", "type": "Colonia"}]}