{"cp": 86960, "municipio": "Balanc\u00e1n", "ciudad": "86939", "estado": "Tabasco", "areas": [{"name": "El Bar\u00ed", "type": "Rancher\u00eda"}, {"name": "Carlos A. Madrazo Becerra", "type": "Ejido"}, {"name": "La Revancha", "type": "Rancher\u00eda"}, {"name": "El Mical", "type": "Pueblo"}, {"name": "Bonanza", "type": "Rancho"}, {"name": "Isla del Carmen", "type": "Rancho"}, {"name": "La Guadalupe", "type": "Rancho"}, {"name": "Corpus Christi", "type": "Rancho"}, {"name": "Las Maravillas", "type": "Rancher\u00eda"}, {"name": "Los G\u00f3mez", "type": "Rancho"}, {"name": "Santa Cruz", "type": "Rancho"}, {"name": "Santa Rosal\u00eda", "type": "Rancho"}, {"name": "El Cambio", "type": "Rancho"}]}