{"cp": 90030, "municipio": "Tlaxcala", "ciudad": "Tlaxcala de Xicoht\u00e9ncatl", "estado": "Tlaxcala", "areas": [{"name": "Felipe Santiago Xicot\u00e9ncatl", "type": "Unidad habitacional"}, {"name": "Los Volcanes", "type": "Unidad habitacional"}, {"name": "Las \u00c1nimas", "type": "Fraccionamiento"}, {"name": "Paso de Cortes", "type": "Fraccionamiento"}, {"name": "Cuarto Se\u00f1or\u00edos", "type": "Unidad habitacional"}, {"name": "Real del Sol", "type": "Fraccionamiento"}, {"name": "Lomas de Coyotepec", "type": "Fraccionamiento"}, {"name": "Las \u00c1nimas", "type": "Unidad habitacional"}, {"name": "Ameyal", "type": "Fraccionamiento"}, {"name": "Residencial Jardines de San Gabriel", "type": "Unidad habitacional"}, {"name": "Villa de los \u00c1ngeles", "type": "Unidad habitacional"}, {"name": "Los Girasoles", "type": "Fraccionamiento"}, {"name": "Los Pinos", "type": "Fraccionamiento"}, {"name": "El Real", "type": "Fraccionamiento"}, {"name": "Los Cipreses", "type": "Fraccionamiento"}]}