{"cp": 90435, "municipio": "Tetla de la Solidaridad", "ciudad": "90431", "estado": "Tlaxcala", "areas": [{"name": "Capulac", "type": "Pueblo"}, {"name": "San Gregorio", "type": "Rancher\u00eda"}, {"name": "La Divina Providencia", "type": "Rancher\u00eda"}, {"name": "Campo David", "type": "Rancher\u00eda"}, {"name": "Felipe Guti\u00e9rrez", "type": "Rancher\u00eda"}, {"name": "Santa Fe la Troje", "type": "Rancher\u00eda"}, {"name": "Guillermo Mac\u00edas", "type": "Rancher\u00eda"}, {"name": "El Pozo", "type": "Rancher\u00eda"}, {"name": "El Prado", "type": "Rancher\u00eda"}, {"name": "Fracci\u00f3n el Derramadero", "type": "Rancher\u00eda"}]}