{"cp": 92686, "municipio": "Ixhuatl\u00e1n de Madero", "ciudad": "92682", "estado": "Veracruz de Ignacio de la Llave", "areas": [{"name": "Tecalco", "type": "Rancher\u00eda"}, {"name": "Achichipic", "type": "Congregaci\u00f3n"}, {"name": "Teopancahuac", "type": "Rancher\u00eda"}, {"name": "La Chaca", "type": "Rancher\u00eda"}, {"name": "Tecanahua", "type": "Rancher\u00eda"}, {"name": "El Becerro", "type": "Rancher\u00eda"}, {"name": "Chapopote", "type": "Rancher\u00eda"}, {"name": "Corral Viejo", "type": "Rancher\u00eda"}, {"name": "Paso Amatitl\u00e1n", "type": "Rancher\u00eda"}, {"name": "Ayolia", "type": "Rancher\u00eda"}, {"name": "Paso de Ayolia", "type": "Rancher\u00eda"}, {"name": "Tepozcalco", "type": "Rancher\u00eda"}, {"name": "Tzocohuite", "type": "Rancher\u00eda"}, {"name": "Lomas del Dorado", "type": "Rancher\u00eda"}, {"name": "Santa Fe", "type": "Rancher\u00eda"}, {"name": "La Reforma", "type": "Rancher\u00eda"}, {"name": "Lechcuatitla", "type": "Rancher\u00eda"}, {"name": "Paso de \u00c1lamo", "type": "Rancher\u00eda"}, {"name": "Tzapalote", "type": "Rancher\u00eda"}, {"name": "Marcialta", "type": "Rancher\u00eda"}]}