{"cp": 94210, "municipio": "Comapa", "ciudad": "94101", "estado": "Veracruz de Ignacio de la Llave", "areas": [{"name": "Sonora", "type": "Pueblo"}, {"name": "San Francisco Nacaxtle", "type": "Pueblo"}, {"name": "San Felipe de Jes\u00fas", "type": "Pueblo"}, {"name": "Paso Pimienta", "type": "Colonia"}, {"name": "El Jobo (Jobo Viejo)", "type": "Colonia"}, {"name": "El Jobo (Jobo Nuevo)", "type": "Ejido"}, {"name": "Boca del Monte", "type": "Pueblo"}, {"name": "Cerritos", "type": "Pueblo"}, {"name": "El Ciruelo", "type": "Colonia"}, {"name": "Monte de Oro", "type": "Rancher\u00eda"}, {"name": "La Pitahaya", "type": "Colonia"}]}