{"cp": 25070, "municipio": "Saltillo", "ciudad": "Saltillo", "estado": "Coahuila de Zaragoza", "areas": [{"name": "Landin", "type": "Colonia"}, {"name": "Lomas de Guadalupe", "type": "Colonia"}, {"name": "Lourdes", "type": "Colonia"}, {"name": "26 de Marzo", "type": "Unidad habitacional"}, {"name": "Privada Obreg\u00f3n Sur", "type": "Fraccionamiento"}, {"name": "Balcones de Landin", "type": "Colonia"}, {"name": "Lomas de Land\u00edn", "type": "Fraccionamiento"}, {"name": "Privada Rinc\u00f3n de Salazar", "type": "Fraccionamiento"}]}