{"cp": 29017, "municipio": "Tuxtla Guti\u00e9rrez", "ciudad": "Tuxtla Guti\u00e9rrez", "estado": "Chiapas", "areas": [{"name": "Agripino Guti\u00e9rrez", "type": "Colonia"}, {"name": "Colinas de Oriente", "type": "Colonia"}, {"name": "Las Lajas", "type": "Fraccionamiento"}, {"name": "Natalia Venegas", "type": "Colonia"}, {"name": "Capulines 1", "type": "Colonia"}, {"name": "Capulines 2", "type": "Fraccionamiento"}, {"name": "Estrada", "type": "Fraccionamiento"}, {"name": "Los Capulines III", "type": "Colonia"}]}