{"cp": 34583, "municipio": "Tamazula", "ciudad": "34581", "estado": "Durango", "areas": [{"name": "Acachuane", "type": "Rancher\u00eda"}, {"name": "Huizolixta", "type": "Rancher\u00eda"}, {"name": "Agua Caliente", "type": "Pueblo"}, {"name": "El Carrizal", "type": "Rancher\u00eda"}, {"name": "Acatita Grande (Acatita)", "type": "Rancher\u00eda"}, {"name": "Amacuable", "type": "Rancher\u00eda"}, {"name": "Chacoal", "type": "Rancher\u00eda"}, {"name": "El Bledal", "type": "Rancher\u00eda"}, {"name": "El Castillo", "type": "Rancher\u00eda"}, {"name": "El Muerto", "type": "Rancher\u00eda"}, {"name": "El Otatal", "type": "Rancher\u00eda"}, {"name": "El Salto", "type": "Rancher\u00eda"}, {"name": "El Tecomate", "type": "Rancher\u00eda"}, {"name": "La Ci\u00e9nega de Otates", "type": "Rancher\u00eda"}, {"name": "La Enramada", "type": "Rancher\u00eda"}, {"name": "La Junta", "type": "Rancher\u00eda"}, {"name": "La Laguna", "type": "Rancher\u00eda"}, {"name": "La Lajita", "type": "Rancher\u00eda"}, {"name": "Las Higueritas", "type": "Rancher\u00eda"}, {"name": "Las Trancas", "type": "Rancher\u00eda"}, {"name": "Los Aguajitos", "type": "Rancher\u00eda"}, {"name": "Los Arrayanes", "type": "Rancher\u00eda"}, {"name": "Los Chapotes", "type": "Rancher\u00eda"}, {"name": "Los Coyotes", "type": "Rancher\u00eda"}, {"name": "Los Medios", "type": "Rancher\u00eda"}, {"name": "Los Otates", "type": "Rancher\u00eda"}, {"name": "Palos Verdes", "type": "Rancher\u00eda"}, {"name": "Potrerillo", "type": "Rancher\u00eda"}, {"name": "San Jos\u00e9 del Rancho", "type": "Rancher\u00eda"}, {"name": "Tacuitapa", "type": "Rancher\u00eda"}, {"name": "Topiba", "type": "Rancher\u00eda"}]}