{"cp": 35079, "municipio": "G\u00f3mez Palacio", "ciudad": "G\u00f3mez Palacio", "estado": "Durango", "areas": [{"name": "Parque Industrial HI-TECH", "type": "Zona industrial"}, {"name": "Industrias Linamar", "type": "Zona industrial"}, {"name": "Ex-Ejido Cuba", "type": "Colonia"}, {"name": "INFONAVIT Jos\u00e9 Campillo Sainz", "type": "Fraccionamiento"}, {"name": "Rinconada del Parque", "type": "Fraccionamiento"}, {"name": "Parque Industrial Carlos A Herrera Araluce", "type": "Zona industrial"}, {"name": "Jard\u00edn", "type": "Fraccionamiento"}, {"name": "Villas las Misiones", "type": "Fraccionamiento"}]}