{"cp": 38198, "municipio": "Apaseo el Grande", "ciudad": "38161", "estado": "Guanajuato", "areas": [{"name": "San Ram\u00f3n", "type": "Rancher\u00eda"}, {"name": "Bomba del Mezquital", "type": "Rancher\u00eda"}, {"name": "Bordo Blanco (Rancho el Sagrado)", "type": "Rancher\u00eda"}, {"name": "Ejido el Jaral", "type": "Ejido"}, {"name": "El Molino de Abajo", "type": "Rancher\u00eda"}, {"name": "El Olvido", "type": "Rancher\u00eda"}, {"name": "El Puente Ingl\u00e9s", "type": "Rancher\u00eda"}, {"name": "Los Jim\u00e9nez (Bordo Blanco)", "type": "Rancher\u00eda"}, {"name": "Ram\u00f3n Lazarini", "type": "Rancher\u00eda"}, {"name": "Rancho la Guadalupana (El Puente Grande)", "type": "Rancher\u00eda"}]}