{"cp": 50663, "municipio": "San Jos\u00e9 del Rinc\u00f3n", "ciudad": "50602", "estado": "M\u00e9xico", "areas": [{"name": "El Capul\u00edn San Miguel del Centro", "type": "Rancher\u00eda"}, {"name": "Guadalupe del Pedregal el Calvario", "type": "Rancher\u00eda"}, {"name": "La Puerta San Miguel del Centro", "type": "Rancher\u00eda"}, {"name": "Las Rosas San Miguel del Centro", "type": "Barrio"}, {"name": "San Francisco de la Loma Segunda Secci\u00f3n", "type": "Rancher\u00eda"}, {"name": "Guarda de Guadalupe", "type": "Pueblo"}, {"name": "Rosa de la Palma", "type": "Rancher\u00eda"}, {"name": "Santa Cruz del Rinc\u00f3n", "type": "Pueblo"}, {"name": "La Soledad el Guarda", "type": "Pueblo"}, {"name": "San Onofre Centro (Carmona)", "type": "Pueblo"}, {"name": "Jes\u00fas Carranza", "type": "Pueblo"}, {"name": "San Miguel del Centro", "type": "Pueblo"}, {"name": "El Porvenir", "type": "Pueblo"}, {"name": "San Francisco Solo", "type": "Pueblo"}, {"name": "Cedro de la Manzana", "type": "Pueblo"}, {"name": "Guadalupe del Pedregal", "type": "Pueblo"}, {"name": "Guadalupe del Pedregal la Palma", "type": "Pueblo"}, {"name": "San Francisco de la Loma", "type": "Pueblo"}, {"name": "Pathe Mula de los Cedros", "type": "Pueblo"}, {"name": "El Consuelo", "type": "Ejido"}, {"name": "San Juan Evangelista Fracci\u00f3n Diez (San Juan)", "type": "Rancher\u00eda"}, {"name": "La Cuadrilla San Miguel del Centro", "type": "Pueblo"}, {"name": "Emiliano Zapata Ampliaci\u00f3n la Mesa", "type": "Colonia"}, {"name": "San Onofre", "type": "Ejido"}, {"name": "El Guarda Ejido", "type": "Rancher\u00eda"}]}