{"cp": 51468, "municipio": "Luvianos", "ciudad": "51441", "estado": "M\u00e9xico", "areas": [{"name": "Agua Colorada", "type": "Rancher\u00eda"}, {"name": "Array\u00e1n", "type": "Rancher\u00eda"}, {"name": "Ca\u00f1ada del Campanario", "type": "Rancher\u00eda"}, {"name": "Chirimoya", "type": "Rancher\u00eda"}, {"name": "Ciprianes", "type": "Pueblo"}, {"name": "Cruz de Clavos", "type": "Pueblo"}, {"name": "El Campanario", "type": "Pueblo"}, {"name": "El Cirian de Hermiltepec", "type": "Pueblo"}, {"name": "El Granjen", "type": "Rancher\u00eda"}, {"name": "Huiztepec", "type": "Rancher\u00eda"}, {"name": "Rinc\u00f3n Cruz de Clavos", "type": "Rancher\u00eda"}, {"name": "Rinc\u00f3n de Ciprianes", "type": "Rancher\u00eda"}]}