{"cp": 55755, "municipio": "Tec\u00e1mac", "ciudad": "Tec\u00e1mac de Felipe Villanueva", "estado": "M\u00e9xico", "areas": [{"name": "Los Reyes Acozac", "type": "Pueblo"}, {"name": "La Campi\u00f1a", "type": "Colonia"}, {"name": "Buenavista", "type": "Colonia"}, {"name": "Guadalupe de Reyes Acozac", "type": "Barrio"}, {"name": "La Michapa", "type": "Colonia"}, {"name": "La Palma de Reyes", "type": "Colonia"}, {"name": "Progreso", "type": "Colonia"}, {"name": "El Calvario de Reyes Acozac", "type": "Barrio"}, {"name": "San Miguel", "type": "Colonia"}]}