{"cp": 60464, "municipio": "Tanc\u00edtaro", "ciudad": "60463", "estado": "Michoac\u00e1n de Ocampo", "areas": [{"name": "Palmito del Poniente", "type": "Rancher\u00eda"}, {"name": "Los Fresnos", "type": "Rancher\u00eda"}, {"name": "Garichico", "type": "Rancher\u00eda"}, {"name": "Pareo", "type": "Pueblo"}, {"name": "El Pinabete", "type": "Rancher\u00eda"}, {"name": "El Reparo (La Presa el Reparo)", "type": "Rancher\u00eda"}, {"name": "El Aguacate Poniente", "type": "Rancher\u00eda"}, {"name": "El Espino", "type": "Rancher\u00eda"}, {"name": "El Moral", "type": "Rancher\u00eda"}, {"name": "La Consentida", "type": "Rancher\u00eda"}, {"name": "La Paja", "type": "Rancho"}, {"name": "Las Canoas", "type": "Rancher\u00eda"}, {"name": "Las Higueras", "type": "Rancher\u00eda"}, {"name": "Los Ojos de Agua", "type": "Rancher\u00eda"}, {"name": "Ojo de Agua (El Ojo de Agua del Palmito)", "type": "Rancher\u00eda"}, {"name": "Pila Honda", "type": "Rancho"}]}