{"cp": 60914, "municipio": "Tumbiscat\u00edo", "ciudad": "60922", "estado": "Michoac\u00e1n de Ocampo", "areas": [{"name": "Aruchita", "type": "Rancher\u00eda"}, {"name": "El Caracol", "type": "Rancher\u00eda"}, {"name": "El Culebro", "type": "Rancher\u00eda"}, {"name": "El Para\u00edso", "type": "Rancher\u00eda"}, {"name": "El Pimientillo", "type": "Rancher\u00eda"}, {"name": "La Herradura (San Juan de los Pl\u00e1tanos)", "type": "Rancher\u00eda"}, {"name": "La Pantomima", "type": "Rancher\u00eda"}, {"name": "Las Mesas", "type": "Rancher\u00eda"}, {"name": "Los Chivos", "type": "Rancher\u00eda"}, {"name": "Mata de Pl\u00e1tano", "type": "Rancher\u00eda"}, {"name": "Graciano S\u00e1nchez (El Socorro)", "type": "Pueblo"}]}