{"cp": 62765, "municipio": "Emiliano Zapata", "ciudad": "62761", "estado": "Morelos", "areas": [{"name": "Ojo de Agua II", "type": "Condominio"}, {"name": "Prohogar", "type": "Colonia"}, {"name": "Benito Ju\u00e1rez", "type": "Colonia"}, {"name": "El Capul\u00edn", "type": "Colonia"}, {"name": "Guadalupe de las Arenas", "type": "Colonia"}, {"name": "El Mirador", "type": "Colonia"}, {"name": "Ampliaci\u00f3n Prohogar", "type": "Colonia"}, {"name": "Ojo de Agua", "type": "Condominio"}, {"name": "Manantiales", "type": "Fraccionamiento"}, {"name": "Los Agaves", "type": "Fraccionamiento"}, {"name": "Palo Escrito (Colonia Benito Ju\u00e1rez)", "type": "Colonia"}]}