{"cp": 62790, "municipio": "Xochitepec", "ciudad": "62791", "estado": "Morelos", "areas": [{"name": "El Crucero de Atlacholoaya", "type": "Colonia"}, {"name": "Campo San Rafael", "type": "Colonia"}, {"name": "La Guamuchilera", "type": "Colonia"}, {"name": "Rinconada de Xochitepec", "type": "Fraccionamiento"}, {"name": "Real del Puente", "type": "Colonia"}, {"name": "Xochitepec Centro", "type": "Colonia"}, {"name": "Benito Ju\u00e1rez", "type": "Colonia"}, {"name": "La Calera", "type": "Colonia"}, {"name": "San Miguel La Uni\u00f3n", "type": "Colonia"}, {"name": "San Pedro de los Pinos", "type": "Colonia"}, {"name": "Morelos 1ra Secci\u00f3n", "type": "Colonia"}, {"name": "Morelos 2da Secci\u00f3n", "type": "Colonia"}, {"name": "Morelos 3ra Secci\u00f3n", "type": "Colonia"}, {"name": "Las Flores", "type": "Colonia"}, {"name": "Loma Bonita", "type": "Colonia"}, {"name": "Obrera Popular", "type": "Colonia"}, {"name": "Nueva Morelos", "type": "Colonia"}, {"name": "Miguel Hidalgo", "type": "Colonia"}, {"name": "Ampliaci\u00f3n Miguel Hidalgo", "type": "Colonia"}, {"name": "3 de Mayo", "type": "Colonia"}, {"name": "San Francisco", "type": "Colonia"}, {"name": "L\u00e1zaro C\u00e1rdenas", "type": "Colonia"}, {"name": "El Pedregal", "type": "Colonia"}, {"name": "Jardines de Xochitepec", "type": "Colonia"}, {"name": "Villas de Xochitepec", "type": "Fraccionamiento"}, {"name": "La Cruz", "type": "Colonia"}, {"name": "Tierra Verde", "type": "Colonia"}, {"name": "Francisco Villa", "type": "Colonia"}, {"name": "La Esperanza", "type": "Colonia"}, {"name": "Campo Canela", "type": "Colonia"}, {"name": "Real del Puente", "type": "Fraccionamiento"}, {"name": "Las Rosas", "type": "Colonia"}, {"name": "Lomas del Manantial", "type": "Colonia"}]}