{"cp": 66450, "municipio": "San Nicol\u00e1s de los Garza", "ciudad": "San Nicol\u00e1s de los Garza", "estado": "Nuevo Le\u00f3n", "areas": [{"name": "An\u00e1huac", "type": "Colonia"}, {"name": "Cuauht\u00e9moc", "type": "Colonia"}, {"name": "Chapultepec", "type": "Colonia"}, {"name": "El Roble", "type": "Colonia"}, {"name": "Lomas del Roble", "type": "Colonia"}, {"name": "Valle de An\u00e1huac", "type": "Colonia"}, {"name": "Royal", "type": "Fraccionamiento"}, {"name": "Pedregal de An\u00e1huac", "type": "Fraccionamiento"}, {"name": "Prival de Anahuac", "type": "Fraccionamiento"}, {"name": "Avita An\u00e1huac", "type": "Fraccionamiento"}, {"name": "Viejo An\u00e1huac", "type": "Colonia"}]}