{"cp": 67958, "municipio": "Aramberri", "ciudad": "67901", "estado": "Nuevo Le\u00f3n", "areas": [{"name": "Ibarrilla (Rinc\u00f3n de Ibarrilla)", "type": "Ejido"}, {"name": "\u00c1lamos", "type": "Ejido"}, {"name": "Duraznillos", "type": "Rancho"}, {"name": "El Divisadero", "type": "Rancho"}, {"name": "El Naranjo", "type": "Rancho"}, {"name": "El Puerto", "type": "Rancho"}, {"name": "El Rinc\u00f3n de Jes\u00fas", "type": "Rancho"}, {"name": "El Sauz", "type": "Rancho"}, {"name": "Esquivel", "type": "Rancho"}, {"name": "Ignacio Zaragoza", "type": "Ejido"}, {"name": "La Gota", "type": "Rancho"}, {"name": "La Tinaja", "type": "Rancho"}, {"name": "Lagunitas", "type": "Rancho"}, {"name": "Las Mulas", "type": "Rancho"}, {"name": "Los Laureles", "type": "Rancho"}, {"name": "Monillal", "type": "Rancho"}, {"name": "Ojo de Agua", "type": "Rancho"}, {"name": "Puerto Rinc\u00f3n de Jes\u00fas", "type": "Rancho"}]}