{"cp": 70737, "municipio": "Santa Mar\u00eda Guienagati", "ciudad": "70111", "estado": "Oaxaca", "areas": [{"name": "Pe\u00f1a Blanca", "type": "Rancher\u00eda"}, {"name": "Arroyo Chino", "type": "Rancher\u00eda"}, {"name": "Cerro Grande", "type": "Rancher\u00eda"}, {"name": "Bustamante", "type": "Colonia"}, {"name": "Jerusal\u00e9n", "type": "Rancher\u00eda"}, {"name": "Lachigux\u00e9", "type": "Rancher\u00eda"}, {"name": "Los Valles", "type": "Rancher\u00eda"}, {"name": "Pie de Cerro", "type": "Rancher\u00eda"}, {"name": "Tres Mar\u00edas", "type": "Rancher\u00eda"}]}