{"cp": 70965, "municipio": "Pluma Hidalgo", "ciudad": "70901", "estado": "Oaxaca", "areas": [{"name": "La Pasionaria", "type": "Rancher\u00eda"}, {"name": "Cruz Grande", "type": "Rancher\u00eda"}, {"name": "Copalita", "type": "Rancher\u00eda"}, {"name": "El Convenio", "type": "Rancher\u00eda"}, {"name": "El F\u00e9nix", "type": "Rancher\u00eda"}, {"name": "El Olivo", "type": "Rancher\u00eda"}, {"name": "El Paisaje", "type": "Ejido"}, {"name": "El Triunfo", "type": "Rancher\u00eda"}, {"name": "El Venado", "type": "Rancher\u00eda"}, {"name": "La Aurora (Los Cruz)", "type": "Rancher\u00eda"}, {"name": "La Garita", "type": "Rancher\u00eda"}, {"name": "La Huerta", "type": "Rancher\u00eda"}, {"name": "La Libertad", "type": "Rancher\u00eda"}, {"name": "La Sirena", "type": "Rancher\u00eda"}, {"name": "La Trinidad", "type": "Rancher\u00eda"}, {"name": "La Venta", "type": "Rancher\u00eda"}, {"name": "Las Trancas", "type": "Rancher\u00eda"}, {"name": "Mirale\u00f3n", "type": "Rancher\u00eda"}, {"name": "Pocitos", "type": "Rancher\u00eda"}, {"name": "Porvenir", "type": "Rancher\u00eda"}, {"name": "San Isidro", "type": "Rancher\u00eda"}, {"name": "San Jacinto", "type": "Rancher\u00eda"}, {"name": "San Juanito", "type": "Rancher\u00eda"}, {"name": "San Lucas", "type": "Rancher\u00eda"}, {"name": "Soledad", "type": "Rancher\u00eda"}]}