{"cp": 73950, "municipio": "Chignautla", "ciudad": "73801", "estado": "Puebla", "areas": [{"name": "Coahuixco", "type": "Pueblo"}, {"name": "Chignautla", "type": "Pueblo"}, {"name": "Sosa", "type": "Rancher\u00eda"}, {"name": "Yopi", "type": "Rancher\u00eda"}, {"name": "San Antonio", "type": "Colonia"}, {"name": "5 de Mayo", "type": "Colonia"}, {"name": "Calicapan", "type": "Colonia"}, {"name": "La Cruz", "type": "Colonia"}, {"name": "Tezohuatepec (Tezotepec)", "type": "Colonia"}, {"name": "La Azteca", "type": "Colonia"}]}