{"cp": 75235, "municipio": "Cuautinch\u00e1n", "ciudad": "75201", "estado": "Puebla", "areas": [{"name": "El Esfuerzo", "type": "Colonia"}, {"name": "San Baltazar Torija", "type": "Pueblo"}, {"name": "Agua Santa", "type": "Colonia"}, {"name": "Cuautenco", "type": "Rancher\u00eda"}, {"name": "El Granado", "type": "Colonia"}, {"name": "La Lobera", "type": "Colonia"}, {"name": "Las Aguilillas", "type": "Ejido"}, {"name": "Tlalcorral", "type": "Ejido"}, {"name": "Zapotetla", "type": "Rancher\u00eda"}]}