{"cp": 76323, "municipio": "Pinal de Amoles", "ciudad": "76301", "estado": "Quer\u00e9taro", "areas": [{"name": "Agua Cazuela", "type": "Rancher\u00eda"}, {"name": "Agua Verde", "type": "Rancher\u00eda"}, {"name": "El Chuveje", "type": "Rancher\u00eda"}, {"name": "El Salto", "type": "Rancher\u00eda"}, {"name": "La Cieneguilla", "type": "Rancher\u00eda"}, {"name": "Joyas del Real", "type": "Pueblo"}, {"name": "San Jos\u00e9 Cochinito", "type": "Rancher\u00eda"}, {"name": "El Cuervo de San Pedro", "type": "Rancher\u00eda"}]}