{"cp": 82136, "municipio": "Mazatl\u00e1n", "ciudad": "Mazatl\u00e1n", "estado": "Sinaloa", "areas": [{"name": "Montebello", "type": "Colonia"}, {"name": "Petr\u00f3leos", "type": "Fraccionamiento"}, {"name": "Jaripillo", "type": "Colonia"}, {"name": "Santa Laura", "type": "Fraccionamiento"}, {"name": "La Campi\u00f1a", "type": "Fraccionamiento"}, {"name": "Bosques del Arroyo", "type": "Fraccionamiento"}, {"name": "Colinas del Real", "type": "Fraccionamiento"}, {"name": "Mar\u00eda Antonieta", "type": "Colonia"}, {"name": "Valle Bonito", "type": "Fraccionamiento"}, {"name": "Villa Tutuli", "type": "Fraccionamiento"}, {"name": "Buenos Aires", "type": "Colonia"}, {"name": "Torremolinos Costa Azul", "type": "Fraccionamiento"}, {"name": "Jos\u00e9 Gordillo Pinto", "type": "Fraccionamiento"}, {"name": "Villa Tutuli II", "type": "Fraccionamiento"}]}