{"cp": 83316, "municipio": "Hermosillo", "ciudad": "83345", "estado": "Sonora", "areas": [{"name": "El Choyudo (Los Japoneses)", "type": "Ejido"}, {"name": "El Colorado", "type": "Ejido"}, {"name": "Tastiota", "type": "Ejido"}, {"name": "Acu\u00edcola Tastiota", "type": "Granja"}, {"name": "Granja Genitch", "type": "Rancher\u00eda"}, {"name": "Crucero Doce y Veintis\u00e9is", "type": "Rancher\u00eda"}, {"name": "El Gato", "type": "Rancher\u00eda"}, {"name": "Lic. Ignacio Ram\u00edrez y su anexo San Pedro [NCPE]", "type": "Rancher\u00eda"}, {"name": "El Pedernal Tres", "type": "Rancher\u00eda"}, {"name": "El Retiro", "type": "Rancher\u00eda"}, {"name": "Floresta", "type": "Rancher\u00eda"}, {"name": "El Sagrado (La Victoria)", "type": "Rancher\u00eda"}, {"name": "El Sauz", "type": "Rancher\u00eda"}, {"name": "Establo la Tesota (Tesota)", "type": "Rancher\u00eda"}, {"name": "San Carlitos", "type": "Rancher\u00eda"}, {"name": "Guadalupe de Jes\u00fas", "type": "Rancher\u00eda"}, {"name": "San Fernando", "type": "Rancher\u00eda"}, {"name": "La Chacra", "type": "Rancher\u00eda"}, {"name": "La Chueca", "type": "Rancher\u00eda"}, {"name": "La Higuerita", "type": "Rancher\u00eda"}, {"name": "Larvas G\u00e9nesis", "type": "Rancher\u00eda"}, {"name": "Las Cadenas", "type": "Rancher\u00eda"}, {"name": "Las Conchas (Tortiller\u00eda)", "type": "Equipamiento"}, {"name": "Las Lilas", "type": "Rancher\u00eda"}, {"name": "Los Corralitos", "type": "Rancher\u00eda"}, {"name": "Los Corralitos", "type": "Ejido"}, {"name": "Los Corralitos", "type": "Rancho"}, {"name": "Mar\u00eda Belem", "type": "Rancher\u00eda"}, {"name": "Nuevo Suaqui", "type": "Rancher\u00eda"}, {"name": "Puerto Arturo", "type": "Ejido"}, {"name": "Rancho Santa Rosa", "type": "Rancher\u00eda"}, {"name": "San Agust\u00edn", "type": "Rancher\u00eda"}, {"name": "San Carlos", "type": "Rancher\u00eda"}, {"name": "San Carlos (El Pocito)", "type": "Rancher\u00eda"}, {"name": "San Francisco (El Sahuaral)", "type": "Rancher\u00eda"}, {"name": "San Gerardo", "type": "Rancher\u00eda"}, {"name": "San Joel", "type": "Rancher\u00eda"}, {"name": "San Miguel", "type": "Rancher\u00eda"}]}