{"cp": 84136, "municipio": "Imuris", "ciudad": "84121", "estado": "Sonora", "areas": [{"name": "Campo Carretero", "type": "Campamento"}, {"name": "El Crucero", "type": "Pueblo"}, {"name": "La Mesa", "type": "Colonia"}, {"name": "Terrenate", "type": "Colonia"}, {"name": "Ca\u00f1ada del Diablo", "type": "Colonia"}, {"name": "Agua Caliente", "type": "Rancher\u00eda"}, {"name": "Babasac", "type": "Ejido"}, {"name": "Cerro del Medio", "type": "Rancher\u00eda"}, {"name": "Dos Bellotas", "type": "Rancher\u00eda"}, {"name": "El \u00c1lamo", "type": "Ejido"}, {"name": "El Alballar", "type": "Rancher\u00eda"}, {"name": "El Carmen", "type": "Rancher\u00eda"}, {"name": "El C\u00famaro", "type": "Rancher\u00eda"}, {"name": "El Coyote (La Quirugue\u00f1a)", "type": "Rancher\u00eda"}, {"name": "El Llano", "type": "Ejido"}, {"name": "El Nogal", "type": "Rancher\u00eda"}, {"name": "El Oso", "type": "Rancher\u00eda"}, {"name": "El Salto", "type": "Rancher\u00eda"}, {"name": "La Cano\u00edta", "type": "Rancher\u00eda"}, {"name": "La Cantina", "type": "Rancher\u00eda"}, {"name": "La Casa de Piedra", "type": "Rancher\u00eda"}, {"name": "La Cieneguita", "type": "Rancher\u00eda"}, {"name": "La Galera", "type": "Rancher\u00eda"}, {"name": "La Laguna", "type": "Rancher\u00eda"}, {"name": "La Quinta Artemisa", "type": "Rancher\u00eda"}, {"name": "Las Cruces", "type": "Rancher\u00eda"}, {"name": "Pearson", "type": "Rancher\u00eda"}, {"name": "Puerta del Caj\u00f3n", "type": "Rancher\u00eda"}]}