{"cp": 85236, "municipio": "Navojoa", "ciudad": "85801", "estado": "Sonora", "areas": [{"name": "Navomora", "type": "Rancher\u00eda"}, {"name": "Pueblo Mayo", "type": "Pueblo"}, {"name": "Av\u00edcola Rancho Grande", "type": "Rancher\u00eda"}, {"name": "Bacame Nuevo", "type": "Rancher\u00eda"}, {"name": "Gilberto Barcel\u00f3", "type": "Rancher\u00eda"}, {"name": "Ejido Ignacio Pesqueira", "type": "Rancher\u00eda"}, {"name": "La Batalla", "type": "Rancher\u00eda"}, {"name": "Pozo Dulce", "type": "Rancher\u00eda"}, {"name": "Raymundo L\u00f3pez", "type": "Rancher\u00eda"}, {"name": "Linda Vista", "type": "Rancher\u00eda"}]}