{"cp": 87503, "municipio": "Valle Hermoso", "ciudad": "Valle Hermoso", "estado": "Tamaulipas", "areas": [{"name": "L\u00f3pez Mateos", "type": "Colonia"}, {"name": "Zapata", "type": "Colonia"}, {"name": "Obrera", "type": "Colonia"}, {"name": "Popular", "type": "Colonia"}, {"name": "El Pedregal", "type": "Colonia"}, {"name": "Las Brisas", "type": "Colonia"}, {"name": "M\u00e9xico", "type": "Colonia"}, {"name": "Moderna", "type": "Colonia"}, {"name": "Norte\u00f1ita", "type": "Colonia"}, {"name": "San Jos\u00e9", "type": "Colonia"}, {"name": "SARH", "type": "Colonia"}, {"name": "Las Palmas", "type": "Colonia"}, {"name": "Jos\u00e9 Garc\u00eda C\u00e1rdenas", "type": "Colonia"}, {"name": "Las Mitras", "type": "Colonia"}, {"name": "INFONAVIT Pedregal", "type": "Colonia"}]}