{"cp": 90278, "municipio": "Tlaxco", "ciudad": "90252", "estado": "Tlaxcala", "areas": [{"name": "Titichilco", "type": "Rancher\u00eda"}, {"name": "San Antonio Chapultepec", "type": "Rancher\u00eda"}, {"name": "Dos Barrancas", "type": "Rancher\u00eda"}, {"name": "San Mart\u00edn", "type": "Rancher\u00eda"}, {"name": "Agua Escondida", "type": "Rancher\u00eda"}, {"name": "Los Polos", "type": "Rancher\u00eda"}, {"name": "Agua Escondida Zotoluca", "type": "Rancher\u00eda"}, {"name": "Seco el Viejo", "type": "Rancher\u00eda"}, {"name": "Los Laureles", "type": "Rancher\u00eda"}, {"name": "Santa Mar\u00eda Zotoluca", "type": "Colonia"}, {"name": "San Jos\u00e9 Atotonilco", "type": "Ejido"}, {"name": "Seco", "type": "Rancher\u00eda"}, {"name": "Santa Cruz Rancho Seco", "type": "Rancher\u00eda"}, {"name": "Campo David", "type": "Rancher\u00eda"}]}