{"cp": 95236, "municipio": "Tlalixcoyan", "ciudad": "95221", "estado": "Veracruz de Ignacio de la Llave", "areas": [{"name": "Verde Maduro", "type": "Rancher\u00eda"}, {"name": "El Venado", "type": "Rancher\u00eda"}, {"name": "Las Mesillas", "type": "Rancher\u00eda"}, {"name": "El Almendro", "type": "Rancher\u00eda"}, {"name": "Santa Eulalia", "type": "Rancher\u00eda"}, {"name": "La Ermita", "type": "Rancher\u00eda"}, {"name": "Palo Gordo", "type": "Rancher\u00eda"}, {"name": "Los Pinos", "type": "Rancher\u00eda"}, {"name": "Los \u00c1ngeles", "type": "Rancher\u00eda"}, {"name": "Casa Blanca", "type": "Rancher\u00eda"}, {"name": "San Pedro", "type": "Rancher\u00eda"}, {"name": "Mata Guitarra", "type": "Rancher\u00eda"}, {"name": "Mata Prieto", "type": "Rancher\u00eda"}, {"name": "El Anzuelo", "type": "Rancher\u00eda"}, {"name": "El Mirador", "type": "Rancher\u00eda"}, {"name": "El Nido del \u00c1guila", "type": "Rancher\u00eda"}, {"name": "Tenacalco", "type": "Rancher\u00eda"}, {"name": "Garrapata", "type": "Rancher\u00eda"}]}