{"cp": 96973, "municipio": "Jes\u00fas Carranza", "ciudad": "96951", "estado": "Veracruz de Ignacio de la Llave", "areas": [{"name": "Adolfo L\u00f3pez Mateos (Zacatal)", "type": "Rancher\u00eda"}, {"name": "Nueva Esperanza", "type": "Pueblo"}, {"name": "Cascajal Dos", "type": "Ejido"}, {"name": "Graciano S\u00e1nchez", "type": "Ejido"}, {"name": "Heriberto Jara Corona", "type": "Ejido"}, {"name": "Josefa Ortiz de Dom\u00ednguez (Tronconada)", "type": "Ejido"}, {"name": "Nuevo Progreso (Las Huertas Medina)", "type": "Rancher\u00eda"}]}